simplepycli/CommandValidator.py
simplepycli/PyCLIApp.py
simplepycli/__init__.py
simplepycli-1.0.1.dist-info/WHEEL
simplepycli-1.0.1.dist-info/LICENSE
simplepycli-1.0.1.dist-info/METADATA
simplepycli-1.0.1.dist-info/RECORD
