Metadata-Version: 2.1
Name: simplepycli
Version: 1.0.1
Summary: A really simple library for interactive python CLIs.
Home-page: https://github.com/adithyay328/SimplePyCLI
Author: Adithya Yerramsetty
Author-email: adithyay@hotmail.com
Requires-Python: >=3.8,<4.0
Classifier: Programming Language :: Python :: 3
Classifier: Programming Language :: Python :: 3.8
Classifier: Programming Language :: Python :: 3.9
Classifier: Programming Language :: Python :: 3.10
Classifier: Programming Language :: Python :: 3.11
Requires-Dist: prompt-toolkit (>=3.0.36,<4.0.0)
Project-URL: Repository, https://github.com/adithyay328/SimplePyCLI
